Metadata-Version: 2.1
Name: Geometry3D_vendored
Version: 0.3.0
Summary: A 3D Geometry Lib
Home-page: https://github.com/m-albert/Geometry3D
Author: Minghao Gou
Author-email: gouminghao@gmail.com
License: GPL
Keywords: analytic geometry intersection 3d
Classifier: Intended Audience :: Developers
Classifier: Intended Audience :: Education
Classifier: Topic :: Education
Classifier: Topic :: Scientific/Engineering :: Mathematics
Classifier: License :: OSI Approved :: GNU General Public License v3 or later (GPLv3+)
Classifier: Programming Language :: Python :: 3
License-File: LICENSE
